nti.recipes.zcml-1.0.0-py2.7-nspkg.pth
nti/recipes/zcml/README.rst
nti/recipes/zcml/__init__.py
nti/recipes/zcml/tests.py
nti.recipes.zcml-1.0.0.dist-info/DESCRIPTION.rst
nti.recipes.zcml-1.0.0.dist-info/METADATA
nti.recipes.zcml-1.0.0.dist-info/RECORD
nti.recipes.zcml-1.0.0.dist-info/WHEEL
nti.recipes.zcml-1.0.0.dist-info/entry_points.txt
nti.recipes.zcml-1.0.0.dist-info/metadata.json
nti.recipes.zcml-1.0.0.dist-info/namespace_packages.txt
nti.recipes.zcml-1.0.0.dist-info/top_level.txt
