Metadata-Version: 2.0
Name: nti.recipes.zcml
Version: 1.0.0
Summary: zc.buildout recipes for writing ZCML
Home-page: http://github.com/NextThought/nti.recipes.zcml
Author: Jason Madden
Author-email: open-source@nextthought.com
License: APACHE 2.0
Keywords: buildout zcml
Platform: UNKNOWN
Classifier: Development Status :: 5 - Production/Stable
Classifier: Intended Audience :: Developers
Classifier: Natural Language :: English
Classifier: Operating System :: OS Independent
Classifier: Programming Language :: Python :: 2
Classifier: Programming Language :: Python :: 2.7
Classifier: Programming Language :: Python :: 3
Classifier: Programming Language :: Python :: 3.5
Classifier: Programming Language :: Python :: 3.6
Classifier: Programming Language :: Python :: Implementation :: CPython
Classifier: Programming Language :: Python :: Implementation :: PyPy
Classifier: Natural Language :: English
Classifier: Framework :: Buildout
Requires-Dist: setuptools
Requires-Dist: zc.buildout (>=2.9.4)
Provides-Extra: test
Requires-Dist: manuel; extra == 'test'
Requires-Dist: zope.testing; extra == 'test'
Requires-Dist: zope.testrunner; extra == 'test'
